setup.py
biaspeech/LICENSE
biaspeech/README.md
biaspeech/__init__.py
biaspeech/biaspeech.py
biaspeech.egg-info/PKG-INFO
biaspeech.egg-info/SOURCES.txt
biaspeech.egg-info/dependency_links.txt
biaspeech.egg-info/requires.txt
biaspeech.egg-info/top_level.txt
biaspeech/bin/arduino-cli
biaspeech/controllers/action.py
biaspeech/controllers/asynch.py
biaspeech/controllers/base.py
biaspeech/data/bia.db
biaspeech/data/arduino/_tmp.py
biaspeech/data/arduino/default/_tmp.py
biaspeech/data/arduino/default/default.ino
biaspeech/data/camera/_tmp.py
biaspeech/data/logs/_tmp.py
biaspeech/data/python/_tmp.py
biaspeech/models/blocks/alexa.py
biaspeech/models/blocks/arduino.py
biaspeech/models/blocks/block.py
biaspeech/models/blocks/camera.py
biaspeech/models/blocks/default.py
biaspeech/models/blocks/display.py
biaspeech/models/blocks/macro.py
biaspeech/models/blocks/netflix.py
biaspeech/models/blocks/python.py
biaspeech/models/blocks/radio.py
biaspeech/models/blocks/tv.py
biaspeech/models/blocks/web.py
biaspeech/models/blocks/youtube.py
biaspeech/models/database/grandma.py
biaspeech/models/database/mia.py
biaspeech/models/database/mia_utils.py
biaspeech/models/openAI/ai.py
biaspeech/models/robot/robot.py
biaspeech/models/speech/prompt.py
biaspeech/utils/config.cfg
biaspeech/utils/config.py
biaspeech/utils/debug.py
biaspeech/utils/lang.py
biaspeech/utils/paraphrase.py
biaspeech/utils/speech2Text.py
biaspeech/utils/text2Speech.py
biaspeech/views/app.py
biaspeech/views/ui.py
biaspeech/views/frame0/man.jpeg
biaspeech/views/frame0/robot.png
biaspeech/views/frame0/woman.jpg