Metadata-Version: 2.1
Name: biaspeech
Version: 0.2.3
Summary: BIA (AI), your AI powered vocal assistant
Author: TylerDDDD
Author-email: makertylerdddd@gmail.com
Keywords: robot,otto,ai,vocal,assistant
Classifier: Development Status :: 3 - Alpha
Classifier: Intended Audience :: Education
Classifier: Programming Language :: Python :: 3
Requires-Dist: nltk
Requires-Dist: openai
Requires-Dist: websockets
Requires-Dist: py3langid
Requires-Dist: pyautogui
Requires-Dist: pyaudio
Requires-Dist: speechrecognition
Requires-Dist: pyttsx3
Requires-Dist: parrot
Requires-Dist: customtkinter
Requires-Dist: pyduinocli
Requires-Dist: pyserial
Requires-Dist: sounddevice
